image_processing_jvlc/__init__.py
image_processing_jvlc/processing/__init__.py
image_processing_jvlc/processing/combination.py
image_processing_jvlc/processing/transformation.py
image_processing_jvlc/utils/__init__.py
image_processing_jvlc/utils/io.py
image_processing_jvlc/utils/plot.py
image_processing_jvlc-0.0.2.dist-info/METADATA
image_processing_jvlc-0.0.2.dist-info/WHEEL
image_processing_jvlc-0.0.2.dist-info/top_level.txt
image_processing_jvlc-0.0.2.dist-info/RECORD
