Metadata-Version: 2.1
Name: image_processing_jvlc
Version: 0.0.2
Summary: Image Processing Package using Skimage
Home-page: https://github.com/joaoVitorLeal/image-processing-package
Author: João Leal
Requires-Python: >=3.5
Requires-Dist: matplotlib
Requires-Dist: numpy
Requires-Dist: scikit-image >=0.16.1
